snelnotuleren/__init__.py
snelnotuleren/client.py
snelnotuleren_sdk-1.2.2.dist-info/LICENSE.txt
snelnotuleren_sdk-1.2.2.dist-info/METADATA
snelnotuleren_sdk-1.2.2.dist-info/WHEEL
snelnotuleren_sdk-1.2.2.dist-info/top_level.txt
snelnotuleren_sdk-1.2.2.dist-info/RECORD
