Metadata-Version: 2.1
Name: snelnotuleren-sdk
Version: 1.2.2
Summary: Python SDK voor de Snelnotuleren.nl API
Home-page: https://github.com/snelnotuleren/python-sdk
Author: Snelnotuleren.nl
Author-email: niels@snelnotuleren.nl
Keywords: notulen,transcriptie,api,webhook
Classifier: Development Status :: 5 - Production/Stable
Classifier: Intended Audience :: Developers
Classifier: License :: OSI Approved :: MIT License
Classifier: Operating System :: OS Independent
Classifier: Programming Language :: Python :: 3
Classifier: Programming Language :: Python :: 3.7
Classifier: Programming Language :: Python :: 3.8
Classifier: Programming Language :: Python :: 3.9
Classifier: Programming Language :: Python :: 3.10
Requires-Python: >=3.7
License-File: LICENSE.txt
Requires-Dist: requests>=2.25.0
